grai_schemas/__init__.py
grai_schemas/base.py
grai_schemas/generics.py
grai_schemas/human_ids.py
grai_schemas/integrations/__init__.py
grai_schemas/integrations/base.py
grai_schemas/integrations/errors.py
grai_schemas/integrations/quarantine.py
grai_schemas/package_definitions.py
grai_schemas/py.typed
grai_schemas/schema.py
grai_schemas/serializers.py
grai_schemas/utilities.py
grai_schemas/v1/__init__.py
grai_schemas/v1/edge.py
grai_schemas/v1/events.py
grai_schemas/v1/generics.py
grai_schemas/v1/merge.py
grai_schemas/v1/metadata/__init__.py
grai_schemas/v1/metadata/edges.py
grai_schemas/v1/metadata/generics.py
grai_schemas/v1/metadata/metadata.py
grai_schemas/v1/metadata/nodes.py
grai_schemas/v1/mock.py
grai_schemas/v1/node.py
grai_schemas/v1/organization.py
grai_schemas/v1/source.py
grai_schemas/v1/workspace.py
grai_schemas-0.2.11.dist-info/LICENSE
grai_schemas-0.2.11.dist-info/METADATA
grai_schemas-0.2.11.dist-info/WHEEL
grai_schemas-0.2.11.dist-info/RECORD
